fixcrypto/__init__.py
fixcrypto/core.py
fixcrypto/errors.py
fixcrypto/file_ops.py
fixcrypto/key_manager.py
fixcrypto/utils.py
fixcrypto-0.8.0.dist-info/licenses/LICENSE
fixcrypto-0.8.0.dist-info/METADATA
fixcrypto-0.8.0.dist-info/WHEEL
fixcrypto-0.8.0.dist-info/top_level.txt
fixcrypto-0.8.0.dist-info/RECORD
